ghoauth/__init__.py
ghoauth/py.typed
ghoauth/uriutils.py
ghoauth/oauth2/__init__.py
ghoauth/oauth2/client_authenticator.py
ghoauth/oauth2/errors.py
ghoauth/oauth2/repository.py
ghoauth/oauth2/request.py
ghoauth/oauth2/server.py
ghoauth/oauth2/token.py
ghoauth/oauth2/validator.py
ghoauth/oauth2/endpoints/__init__.py
ghoauth/oauth2/endpoints/abc.py
ghoauth/oauth2/endpoints/authorization.py
ghoauth/oauth2/endpoints/token.py
ghoauth/oauth2/grant_types/__init__.py
ghoauth/oauth2/grant_types/abc.py
ghoauth/oauth2/grant_types/authorization_code.py
ghoauth/oauth2/grant_types/implicit.py
ghoauth/oauth2/grant_types/jwt_bearer.py
ghoauth/oauth2/grant_types/multiple_valued.py
ghoauth/oauth2/grant_types/refresh_token.py
ghoauth/openidconnect/__init__.py
ghoauth/openidconnect/discovery.py
ghoauth/openidconnect/grant_types.py
ghoauth/openidconnect/repository.py
ghoauth/openidconnect/request.py
ghoauth/openidconnect/validator.py
ghoauth-0.8.0.dist-info/LICENSE
ghoauth-0.8.0.dist-info/METADATA
ghoauth-0.8.0.dist-info/WHEEL
ghoauth-0.8.0.dist-info/top_level.txt
ghoauth-0.8.0.dist-info/RECORD
