Metadata-Version: 2.1
Name: ghoauth
Version: 0.8.0
Summary: OAuth Provider Library for Python 3
Author-email: Kohei YOSHIDA <kohei.yoshida@gehirn.co.jp>
Project-URL: Repository, https://github.com/GehirnInc/ghoauth.git
Classifier: Development Status :: 4 - Beta
Classifier: Intended Audience :: Developers
Classifier: License :: OSI Approved :: Apache Software License
Classifier: Operating System :: OS Independent
Classifier: Programming Language :: Python :: 3
Classifier: Programming Language :: Python :: 3 :: Only
Classifier: Topic :: Internet :: WWW/HTTP
Classifier: Topic :: Security
Requires-Python: >=3.8
License-File: LICENSE
Requires-Dist: WebOb~=1.8
Requires-Dist: jwt~=1.2
Requires-Dist: python-jose[cryptography]~=3.0
Requires-Dist: rfc3986~=1.4
Provides-Extra: dev
Requires-Dist: black~=24.8.0; extra == "dev"
Requires-Dist: isort~=5.12; extra == "dev"
Requires-Dist: mypy~=1.11; extra == "dev"
Provides-Extra: test
Requires-Dist: pytest~=8.0; extra == "test"
Requires-Dist: pytest-cov~=5.0; extra == "test"
